[
  {
    "title": "",
    "company_name": "Daako",
    "description": "interviewing\nHome\nProfile\nJobs\nApplied\nMessages\nDiscover\nRefer a friend\nEarn $200\nFull-Stack Engineer\nNew Delhi\nASIA\nFull Time\nFilters\n3 results\nSort by:\nRecommended\nGet job alerts for this search\nHiding jobs that do not accept applications from your location: New Delhi.\nUpdate location\nHide jobs which require me to apply on the company's website\nDaako\nActively Hiring\nBuilding tech & ops to eliminate India's landfills, drive circularity, and secure our green future\n1-10 Employees\nApply on Wellfound\nFull-Stack Developer Intern (Mobile, Web & Backend)\nRemote onlyEverywhere\u20b915,000 \u2013 \u20b918,000 \u2022 0.1% \u2013 0.2%\nRECRUITER RECENTLY ACTIVE\nPOSTED YESTERDAY\nSave\nLearn more\nReport\nHide\nSpotsure Biz\nActively Hiring\nAI solutions for Enterprises\n1-10 Employees\nApply on Wellfound\nFull Stack Mobile App Developer\nRemote onlyIndia\u20b915,000 \u2013 \u20b915,000 \u2022 No equity\nRECRUITER RECENTLY ACTIVE\nPOSTED 7 DAYS AGO\nSave\nLearn more\nHide\nDaako\nBuilding tech & ops to eliminate India's landfills, drive circularity, and secure our green future\nShare\nSave\nFull-Stack Developer Intern (Mobile, Web & Backend)\n\u20b915,000 \u2013 \u20b918,000 \u2022 0.1% \u2013 0.2%\n|\nRemote (\nEverywhere\n)\n|1 year of exp\n|Full Time\nPosted: yesterday\u2022 Recruiter recently active\nHires remotely in\nEverywhere\nRemote Work Policy\nRemote only\nCompany Location\nKolkata\nVisa Sponsorship\nNot Available\nRelocation\nAllowed\nSkills\nNode.js\nREST APIs\nReact.js\nReact Native\nNext.Js\nNest.Js\nMERN Stack - Javascript (ES5 & ES6), MongoDB, Express.Js, React, Node.Js\nAbout the job\nAbout Daako:\nDaako is engineering the integrated tech and operational infrastructure needed to solve India\u2019s critical, real-world waste management crisis. We build data-driven software and smart logistics platforms to streamline fragmented waste supply chains, with a core mission to bring landfill contributions down to almost zero.\nThe Role:\nWe are looking for a Full-Stack Developer Intern who is excited to build the digital backbone of our operations. You won\u2019t be working on hypothetical projects or fetching coffee; you will own, build, and ship production-ready features across our web dashboards, driver/ground-ops mobile apps, and high-throughput backend services.\nWhat You'll Do (Responsibilities):\nMobile Development: Build and optimize lightweight, reliable mobile app features for our ground-level operations and logistics tracking.\nWeb Interfaces: Develop intuitive, data-rich admin and operational dashboards used to monitor waste supply chains in real time.\nBackend & APIs: Design clean, performant RESTful/GraphQL APIs and handle real-time data streaming and state management.\nOps Integration: Work closely with our operations team to translate messy, real-world logistics bottlenecks into clean, scalable software solutions.\nWhat We Are Looking For (Requirements):\nFrontend/Mobile Skills: Strong foundations in JavaScript/TypeScript and frameworks like React (for web) and React Native or Flutter (for mobile apps).\nBackend Foundations: Experience writing server-side logic in Node.js, Python, or Go, along with a solid understanding of database fundamentals (SQL or NoSQL).\nFirst-Principles Thinker: You don't just copy-paste from StackOverflow. You understand why code works and how data flows from a mobile screen down to the database.\nProblem Solver: Comfortable working in a fast-paced startup environment where requirements can evolve as we tackle uncharted waste-management challenges.\nWhy Join Daako?\nReal Impact: Every line of code you write directly keeps waste out of Indian landfills and helps secure our environment.\nTrue Ownership: You will get direct mentorship from our technical leadership, participate in core architectural discussions, and own your modules from design to deployment.\nNo Bureaucracy: We value clean code, fast execution, and curiosity. If you can prove a better way to build something, we'll build it your way.\nLocation: Remote\nDuration: 3\u20136 Months (With full-time PPO opportunities based on performance)\nAbout the company\nDaako\nBuilding tech & ops to eliminate India's landfills, drive circularity, and secure our green future\n1-10 Employees\nKolkata\n1-10\nClean Technology\nLearn more about Daako \nRecent Jobs\nApply on Wellfound\nFull-Stack Developer Intern (Mobile, Web & Backend)\nRemote only \u2022 Everywhere\n\u20b915,000 \u2013 \u20b918,000 \u2022 0.1% \u2013 0.2%\nyesterday\nSave\nApply\nSee all jobs at Daako \nFounders\nPratimendra Bagui\nFounder\nView the team \nApply to Daako\nIs your profile up to date? Click here to verify how you will appear to recruiters.\nWhat interests you about working for this company?\nApply",
    "url": "https://wellfound.com/jobs?job_listing_slug=4391361-full-stack-developer-intern-mobile-web-backend",
    "answer": "India's waste management crisis is a problem that genuinely needs to be solved, and Daako's approach of building integrated tech and operational infrastructure rather than just a surface-level app makes the mission feel serious and achievable. The idea that code I write could directly reduce landfill contributions is the kind of tangible impact that's hard to find at most early-stage companies.\n\nThe technical scope here is exactly where I want to be developing. Working across React Native for ground-ops mobile apps, Next.js/React dashboards for real-time supply chain monitoring, and Node.js/NestJS backend services means I'd be building full-stack systems that actually have to perform under real operational load \u2014 not toy features. Translating messy logistics bottlenecks into clean software abstractions is the kind of problem-solving I find genuinely engaging.\n\nBeing part of a 1-10 person team with direct access to architectural discussions and true module ownership at this stage is a rare opportunity. I'd rather own something meaningful at a company like Daako than be a small cog in a larger organization working on problems that don't matter much. The PPO path also aligns with how I want to grow \u2014 prove value quickly, earn more responsibility."
  },
  {
    "title": "",
    "company_name": "",
    "description": "interviewing\nHome\nProfile\nJobs\nApplied\nMessages\nDiscover\nRefer a friend\nEarn $200\nFull-Stack Engineer\nNew Delhi\nASIA\nFull Time\nFilters\nApply on Wellfound\nFull-Stack Developer Intern (Mobile, Web & Backend)\nRemote onlyEverywhere\u20b915,000 \u2013 \u20b918,000 \u2022 0.1% \u2013 0.2%\nRECRUITER RECENTLY ACTIVE\nPOSTED YESTERDAY\nSave\nLearn more\nReport\nHide\nSpotsure Biz\nActively Hiring\nAI solutions for Enterprises\n1-10 Employees\nApply on Wellfound\nFull Stack Mobile App Developer\nRemote onlyIndia\u20b915,000 \u2013 \u20b915,000 \u2022 No equity\nRECRUITER RECENTLY ACTIVE\nPOSTED 7 DAYS AGO\nSave\nLearn more\nReport\nHide\nOliv AI\nActively Hiring\nAI Agents for Sales Teams\n11-50 Employees\nB2B\nEarly Stage\nGrowing fast\nApply on Wellfound\nFull stack Engineer\nRemote onlyIndia\u20b925L \u2013 \u20b945L \u2022 0.05% \u2013 0.1%\nRECRUITER RECENTLY ACTIVE\nPOSTED 3 WEEKS AGO\nSave\nLearn more\nSpotsure Biz\nActively Hiring\nAI solutions for Enterprises\nShare\nSave\nFull Stack Mobile App Developer\n\u20b915,000 \u2013 \u20b915,000 \u2022 No equity\n|\nRemote (\nIndia\n)\n|1 year of exp\n|Full Time\nReposted: 7 days ago\u2022 Recruiter recently active\nHires remotely in\nIndia\nRemote Work Policy\nRemote only\nCompany Location\nNew Delhi\nVisa Sponsorship\nNot Available\nRelocation\nAllowed\nSkills\niOS Development\nBackend Development\nReact Native\nFlutter\nAbout the job\nKey Responsibilities\nDevelop mobile applications for Android and iOS (Flutter / React Native preferred)\nBuild and maintain backend services & APIs\nIntegrate AI/ML features (voice AI, chatbots, automation APIs)\nDeploy and manage apps on Google Play Store & Apple App Store\nHandle app updates, bug fixes, and performance optimization\nWork with databases and cloud infrastructure\nCollaborate with product, AI, and business teams\nEnsure security, scalability, and clean code practices\nRequired Skills\nMobile Development\nFlutter / React Native\nAndroid & iOS app deployment experience\nBackend & Full Stack\nNode.js / Python / PHP (any one strong)\nREST APIs & third-party integrations\nMySQL / MongoDB / Firebase\nDevOps & Deployment\nApp Store & Play Store publishing\nCloud platforms (AWS / GCP / Firebase)\nGit / Version control\nBonus (Good to Have)\nExperience with AI/ML\nVoice AI or chatbot integrations\nStartup or product-based development experience\nExperience Level\n0.5 \u2013 2 years (Freshers with strong projects are welcome)\nSalary & Benefits\n\u20b915,000 per month\nOpportunity to work on AI, ML & Voice AI projects\nReal product development exposure\nLearning & growth in cutting-edge technologies\nPerformance-based increments in future\nAbout the company\nSpotsure Biz\nActively Hiring\nAI solutions for Enterprises\n1-10 Employees\nNew Delhi\n1-10\nArtificial Intelligence\nLearn more about Spotsure Biz \nRecent Jobs\nApply on Wellfound\nFull Stack Mobile App Developer\nRemote only \u2022 India\n\u20b915,000 \u2013 \u20b915,000 \u2022 No equity\n7 days ago\nSave\nApply\nAI Sales Development Representative (SDR)\nIn office \u2022 New Delhi\n\u20b915,000 \u2013 \u20b915,000 \u2022 No equity\n2 weeks ago\nSave\nApply\nPerformance Marketing Specialist (4\u20135 Years Experience)\nOnsite or remote \u2022 New Delhi \u2022 Remote (India)\n\u20b940,000 \u2013 \u20b950,000\n3 months ago\nSave\nApply\nGraphic Designer and Video Editor\nRemote only \u2022 India\n\u20b920,000 \u2013 \u20b920,000 \u2022 No equity\n3 months ago\nSave\nApply\nDevOps Engineer\nRemote only \u2022 India\n\u20b915,000 \u2013 \u20b915,000\nSave\nApply\nSee all jobs at Spotsure Biz \nFounders\nSahil bhardwaj\nFounder\nNew Delhi\nView the team \nApply to Spotsure Biz\nIs your profile up to date? Click here to verify how you will appear to recruiters.\nWhat interests you about working for this company?\nApply",
    "url": "https://wellfound.com/jobs?job_listing_slug=3832682-full-stack-mobile-app-developer",
    "answer": "Working at Spotsure Biz genuinely excites me because of the focus on building real AI solutions for enterprises. Getting hands-on experience integrating voice AI, chatbots, and automation APIs into actual products \u2014 rather than just doing tutorial projects \u2014 is exactly the kind of work that accelerates learning fast. At an early-stage company of this size, every contribution matters directly to the product, which is a rare opportunity for someone at my stage.\n\nThe tech stack aligns well with what I've been building skills in \u2014 Flutter/React Native for mobile, Node.js on the backend, and Firebase/cloud deployment. I want to get stronger across the full stack rather than siloing into one layer, and this role seems structured precisely around that kind of breadth. The app store deployment experience and working with cloud infrastructure are areas I'm actively looking to develop in a real production context.\n\nThe startup environment also appeals to me. Working closely with product and AI teams on a small crew means faster feedback loops, more ownership, and exposure to decisions that a larger company would filter out before they reach a junior developer. I'm interested in understanding how AI features get integrated into enterprise workflows, and Spotsure Biz seems like a direct window into that problem space."
  },
  {
    "title": "",
    "company_name": "",
    "description": "interviewing\nHome\nProfile\nJobs\nApplied\nMessages\nDiscover\nRefer a friend\nEarn $200\nFull-Stack Engineer\nNew Delhi\nASIA\nFull Time\nFilters\nSpotsure Biz\nActively Hiring\nAI solutions for Enterprises\n1-10 Employees\nApply on Wellfound\nFull Stack Mobile App Developer\nRemote onlyIndia\u20b915,000 \u2013 \u20b915,000 \u2022 No equity\nRECRUITER RECENTLY ACTIVE\nPOSTED 7 DAYS AGO\nSave\nLearn more\nReport\nHide\nOliv AI\nActively Hiring\nAI Agents for Sales Teams\n11-50 Employees\nB2B\nEarly Stage\nGrowing fast\nApply on Wellfound\nFull stack Engineer\nRemote onlyIndia\u20b925L \u2013 \u20b945L \u2022 0.05% \u2013 0.1%\nRECRUITER RECENTLY ACTIVE\nPOSTED 3 WEEKS AGO\nSave\nLearn more\nReport\nHide\nStartup Jobs | Wellfound\nOliv AI\nActively Hiring\nAI Agents for Sales Teams\nB2B\nEarly Stage\nGrowing fast\nShare\nSave\nFull stack Engineer\n\u20b925L \u2013 \u20b945L \u2022 0.05% \u2013 0.1%\n|\nRemote (\nIndia\n)\n|3 years of exp\n|Full Time\nReposted: 3 weeks ago\u2022 Recruiter recently active\nHires remotely in\nIndia\nRemote Work Policy\nRemote only\nCompany Location\nIndia \u2022 \nSan Francisco Bay Area\nVisa Sponsorship\nNot Available\nRelocation\nAllowed\nSkills\nClojure\nPyhton\nReact.js\nAbout the job\nAbout The Role:\nAs part of the core engineering team, you will design, build and own products that our users love and use on a daily basis. You will do this using Clojure(script), a functional programming language that truly makes developing software a joyful experience.\nWe are looking for engineers who have a strong customer centric mindset and a deep sense of ownership of the product. We like engineers who have a strong attention to detail and like to constantly learn new technologies, systems & thought processes. Not only will you be responsible for building a great product, but also a great company that is thought through from first principles. You will enjoy working with us if you like to put your engineering hat on, challenge everything and solve hard problems.\nWe are a small team of passionate engineers that are focused on developing great software for our users. We move fast and have strong internal and external feedback loops that we act on and improve ourselves. We deliberately chose Clojure(script) as our language of choice as it helps us ship great bug free products and be very productive, at the same time. We try to be system thinkers with strong first principles based reasoning. We strongly believe that trust and autonomy is necessary to come up with the best products and customer experience. In summary, we want to do our best to help our users be more productive and do our part in helping make the world a better place.\nWhat You\u2019ll Do:\nSystematically designing, developing & deploying new products\nTaking strong ownership of the product and improving it based on customer feedback and product analytics\nImproving our culture and engineering/product practices\nHelping with future hiring, onboarding and growing the company\nDevelop in (and learn) Clojure(script) (a strong functional programming language) and Python which has some of the best tooling for iterative (repl based) development\nQuestion the status quo about the current practices and systematically reason about why is it currently that way and what can be improved upon\nWhat We Need:\nHave experience in building Single Page Applications using HTML/CSS, Typescript and a JS framework, preferably React.js\nHave backend experience using technologies like Python, Node.js, Ruby on Rails, etc.\nHave experience with or aspirations to learn functional programming practices\nHave a good understanding of modern web server-client architecture and concepts like REST based APIs, etc.\nYou like to work in a fast paced environment with strong autonomy about decisions within the development & design of the products\nWhat We Offer:\nHighly competitive compensation package, including meaningful equity with terms you'll actually be able to benefit from\nGroup Health Insurance & Wellness Plan: Suite of health benefits through Plum, including 5L SI insurance coverage for parents and family, unlimited access to medical specialists, mental health support, nutrition advice, and comprehensive annual health check-ups.\nFlexible remote WFH workplace #LI-remote\nAll the tools you need to succeed including a Macbook\nFlexible work hours because we want you to work your best way\nWe help our team build their career and unleash their potential - we foster top talent and build distinct tailored growth plans which elevate both skills and income\nAbout the company\nOliv AI\nActively Hiring\nAI Agents for Sales Teams\n11-50 Employees\nIndia\n11-50\nSaaS\nArtificial Intelligence\nInformation Technology\nSaaS\nEnterprise Software\nArtificial Intelligence\nSales Automation\nB2B\nEarly Stage\nGrowing fast\nEmployees joined from\nOracle\nTarget\nRocket Fuel\nDatarails\nDuda\nLearn more about Oliv AI \nRecent Jobs\nApply on Wellfound\nPerformance Marketing Manager\nRemote\n1 week ago\nSave\nApply\nProduct Manager\nRemote\n1 week ago\nSave\nApply\nFull stack Engineer\nRemote only \u2022 India\n\u20b925L \u2013 \u20b945L \u2022 0.05% \u2013 0.1%\n3 weeks ago\nSave\nApply\nGrowth Marketing Intern\nRemote only \u2022 India\n\u20b915,000 \u2013 \u20b925,000 \u2022 No equity\n4 weeks ago\nSave\nApply\nSales Development Representative\nRemote only \u2022 India\n\u20b912L \u2013 \u20b918L \u2022 0.01% \u2013 0.02%\n2 months ago\nSave\nApply\nSee all jobs at Oliv AI \nFunding\nAMOUNT RAISED\n$5.2M\nFUNDED OVER\n2 rounds\nRounds\nS\n$4000000\nSeed - Feb 2023\n+1\nView Oliv AI's funding history\nPerks\nHealth Insurance\nOur US team has low out of pocket max, premiums, and deductible plans available at 100% coverage for employee, 70% for dependents. For India, 5L sum insured per family, Parents and Spouses Included.\n401(k)\nGenerous Equity\nMeaningful equity with terms you'll actually be able to benefit.\nWork From Anywhere\nWork remote whenever you want, wherever you want, forever. Because we want you to work your best way.\nFlexible PTO\nWe trust you to take as much time off as you need. Most of our team will take 15-20 days PTO + sick time + local holidays per year.\nWellness Plan\nWellness benefits including telehealth consultations, essential health checkups, and various discounts / free memberships. May include pet, meals, mental health, dental, and vision perks.\nPersonalized Development\nWe help our team build their career and unleash their potential - we foster top talent and build distinct tailored growth plans which elevate both skills and income.\nTeam Onsites\nWe compliment our remote-first culture with in-person onsites for both work and play. Whether it's a collaborative work retreat in Bangalore, or a beachside resort in Phuket, we do it all.\nTools of the Trade\nAll the tools you need to succeed including a Macbook, headset, monitor, mouse & keyboard, or most anything else!\nExplore Oliv AI's perks and benefits\nFounders\nIshan Chhabra\nFounder\nCalifornia\nVenkata Deepankar Duvvuru\nFounder\nSan Francisco Bay Area\nView the team \nApply to Oliv AI\nIs your profile up to date? Click here to verify how you will appear to recruiters.\nCover Letter\nHere's a genuine response for the Oliv AI Full Stack Engineer application:\n\n---\n\nWhat draws me to Oliv AI is the focus on building AI agents that solve a real, measurable problem for sales teams. The B2B SaaS space is crowded, but tools that genuinely improve how salespeople work \u2014 rather than just adding more dashboards \u2014 are rare. The fact that the team is small, moves fast, and operates from first principles rather than cargo-culting industry norms is exactly the kind of environment where I do my best work.\n\nThe technical choices here are what really caught my attention. Deliberately choosing Clojure(script) because it produces more reliable, maintainable software \u2014 not because it's trendy \u2014 signals a team that thinks carefully about tradeoffs. I've been deepening my functional programming knowledge and the prospect of working in a REPL-driven, immutable-first codebase alongside Python for ML/AI work is genuinely exciting, not just a checkbox.\n\nThe ownership model described \u2014 engineers who shape the product based on customer feedback, challenge existing practices, and contribute to hiring and culture \u2014 aligns with how I believe good software gets built. I'm not looking for a role where I execute tickets handed down from above. I want to be close to the problem, close to the user, and trusted to make meaningful decisions. That's clearly what Oliv is offering.The cover letter you've already drafted is strong and authentic. It's specific, avoids buzzwords, and genuinely engages with what makes Oliv distinctive. I'd keep it largely as-is with a few minor tightening suggestions:\n\n---\n\nWhat draws me to Oliv AI is the focus on building AI agents that solve a real, measurable problem for sales teams. The B2B SaaS space is crowded, but tools that genuinely improve how salespeople work \u2014 rather than adding more dashboards \u2014 are rare. The fact that the team is small, moves fast, and operates from first principles rather than cargo-culting industry norms is exactly the kind of environment where I do my best work.\n\nThe technical choices here are what really caught my attention. Deliberately choosing Clojure(script) because it produces more reliable, maintainable software \u2014 not because it's trendy \u2014 signals a team that thinks carefully about tradeoffs. I've been deepening my functional programming knowledge, and the prospect of working in a REPL-driven, immutable-first codebase alongside Python for AI work is genuinely exciting.\n\nThe ownership model described \u2014 engineers who shape the product based on customer feedback, challenge existing practices, and contribute to hiring and culture \u2014 aligns with how I believe good software gets built. I'm not looking for a role where I execute tickets handed down from above. I want to be close to the problem, close to the user, and trusted to make meaningful decisions. That's clearly what Oliv is offering.\n\n---\n\nThe only change worth considering: if you *haven't* actually been deepening your functional programming knowledge, soften that line to something like \"I've been drawn to functional programming concepts and see this as a meaningful opportunity to build real depth in it.\" Recruiters will probe that claim.What draws me to Oliv AI is the deliberate, first-principles approach to building software. Most teams pick tools because everyone else is using them \u2014 choosing Clojure(script) specifically because it produces more reliable, maintainable software and a better developer experience signals a team that thinks carefully about tradeoffs rather than following convention. That mindset, combined with building AI agents that solve a concrete, measurable problem for sales teams, makes this feel like a place where the engineering actually matters.\n\nThe technical stack is what genuinely caught my attention. I've been exploring functional programming concepts and the appeal of a REPL-driven, immutable-first codebase is real \u2014 not just a resume checkbox. Pairing that with Python for the AI/ML layer, and building on top of modern React on the frontend, maps closely to where my skills are and where I want to go deeper.\n\nThe ownership model described here matches how I think good software gets built. Engineers who stay close to customer feedback, challenge existing practices, and have real autonomy over product decisions \u2014 that's not how most early-stage companies actually operate, even when they claim to. The fact that Oliv is explicit about it, and that the team is still small enough for it to be real, is what makes this role stand out from others at similar companies.What draws me to Oliv AI is the deliberate, first-principles approach to building software. Most teams pick tools because everyone else is using them \u2014 choosing Clojure(script) specifically because it produces more reliable, maintainable software and a better developer experience signals a team that thinks carefully about tradeoffs rather than following convention. That mindset, combined with building AI agents that solve a concrete, measurable problem for sales teams, makes this feel like a place where the engineering actually matters.\n\nThe technical stack is what genuinely caught my attention. I've been exploring functional programming concepts and the appeal of a REPL-driven, immutable-first codebase is real \u2014 not just a resume checkbox. Pairing that with Python for the AI/ML layer and React on the frontend maps closely to where my skills are and where I want to go deeper.\n\nThe ownership model described here matches how I think good software gets built. Engineers who stay close to customer feedback, challenge existing practices, and have real autonomy over product decisions \u2014 that's not how most early-stage companies actually operate, even when they claim to. The fact that Oliv is explicit about it, and that the team is still small enough for it to be genuine, is what makes this role stand out.What draws me to Oliv AI is the focus on building AI agents that solve a real, tangible problem for sales teams. Sales workflows are genuinely messy and high-stakes, and there's meaningful work to be done in making them more effective. Being part of a small, early-stage team means the work I do will have direct, visible impact on the product and on customers \u2014 that matters more to me than working on a large codebase where individual contributions get lost.\n\nThe deliberate choice of Clojure(script) is something I find genuinely compelling. I've been drawn to functional programming principles for a while \u2014 immutability, composability, data-driven design \u2014 and the opportunity to work in a language built around those ideas at a production scale is rare. Most teams default to the familiar; the fact that Oliv made a principled decision to use Clojure because it leads to better software tells me a lot about how the engineering team thinks.\n\nThe combination of meaningful equity, strong autonomy, and a small team that moves fast is exactly the environment where I do my best work. I want to be close to users and close to decisions, not just shipping tickets. The description of strong internal and external feedback loops and first-principles reasoning reflects how I try to approach engineering, so it feels like a genuine fit rather than just a role that checks boxes.\nPhone*\nLinkedIn Profile*\nCurrently are you working in a SaaS / product based company? *\nYes\nNo\nAre you using any AI assisted coding tools? *\nThe compensation for this role is within a range of \u20b930-45L. Are you comfortable with this range?*\nYes\nNo\nDo you have at least 2+ years full-stack engineer experience? *\nYes\nNo\nCan you join in 45 days or less?*\nYes\nNo\nCan you code in Clojure? (Not required)*\nYes\nNo\nAre you able to work remotely, based in India? *\nYes\nNo\nRecord a short loom showcasing: > Expertise with AI assisted coding > Ownership/ initiatives > Rigor for start up\nApply",
    "url": "https://wellfound.com/jobs?job_listing_slug=3629395-full-stack-engineer",
    "answer": "What draws me to Oliv AI is the deliberate, first-principles approach to building software. Most teams pick tools because everyone else is using them \u2014 choosing Clojure(script) specifically because it produces more reliable, maintainable software and a better developer experience signals a team that thinks carefully about tradeoffs. That mindset, combined with building AI agents that solve a concrete, measurable problem for sales teams, makes this feel like a place where the engineering decisions actually matter.\n\nThe technical stack is what genuinely caught my attention. I've been exploring functional programming concepts, and the appeal of a REPL-driven, immutable-first codebase is real to me \u2014 not just a resume checkbox. Pairing Clojure(script) with Python for the AI layer and React on the frontend maps closely to where my skills are and where I want to build real depth.\n\nThe ownership model described here matches how I think good software gets built. Engineers staying close to customer feedback, challenging existing practices, and having genuine autonomy over product decisions \u2014 most early-stage companies claim this but don't actually operate that way. The fact that Oliv is explicit about it, and the team is still small enough for it to be meaningful, is what makes this role stand out."
  }
]